{
  "name": "edas",
  "baseNS": "http://edas#",
  "classCount": 103,
  "root": {
    "depth": 0,
    "name": "Thing",
    "subClasses": [
      {
        "depth": 1,
        "name": "Person",
        "subClasses": [
          {
            "depth": 2,
            "name": "ConferenceChair",
            "subClasses": []
          },
          {
            "depth": 2,
            "name": "TPCMember",
            "subClasses": []
          },
          {
            "depth": 2,
            "name": "Attendee",
            "subClasses": []
          },
          {
            "depth": 2,
            "name": "SessionChair",
            "subClasses": []
          }
        ]
      },
      {
        "depth": 1,
        "name": "SingleLevelConference",
        "subClasses": []
      },
      {
        "depth": 1,
        "name": "Topic",
        "subClasses": [
          {
            "depth": 2,
            "name": "MicroelectronicsTopic",
            "subClasses": []
          },
          {
            "depth": 2,
            "name": "MultimediaTopic",
            "subClasses": []
          },
          {
            "depth": 2,
            "name": "SignalProcessingTopic",
            "subClasses": []
          },
          {
            "depth": 2,
            "name": "CommunicationsTopic",
            "subClasses": []
          },
          {
            "depth": 2,
            "name": "OperatingTopicsystems",
            "subClasses": []
          },
          {
            "depth": 2,
            "name": "CryptographyTopic",
            "subClasses": []
          },
          {
            "depth": 2,
            "name": "ParallelAndDistributedComputingTopic",
            "subClasses": []
          },
          {
            "depth": 2,
            "name": "ComputerArchitectureTopic",
            "subClasses": []
          },
          {
            "depth": 2,
            "name": "SatelliteAndSpaceCommunicationsTopic",
            "subClasses": []
          },
          {
            "depth": 2,
            "name": "MedicineTopic",
            "subClasses": []
          },
          {
            "depth": 2,
            "name": "TestOnlyTopic",
            "subClasses": []
          },
          {
            "depth": 2,
            "name": "CADTopic",
            "subClasses": []
          },
          {
            "depth": 2,
            "name": "SecurityTopic",
            "subClasses": []
          },
          {
            "depth": 2,
            "name": "RadioCommunicationsTopic",
            "subClasses": []
          },
          {
            "depth": 2,
            "name": "CommunicationTheoryTopic",
            "subClasses": []
          },
          {
            "depth": 2,
            "name": "AntennasTopic",
            "subClasses": []
          },
          {
            "depth": 2,
            "name": "WirelessCommunicationsTopic",
            "subClasses": []
          },
          {
            "depth": 2,
            "name": "ComputerNetworksTopic",
            "subClasses": [
              {
                "depth": 3,
                "name": "ComputerNetworksSecurityTopic",
                "subClasses": []
              },
              {
                "depth": 3,
                "name": "ComputerNetworksMeasurementsTopic",
                "subClasses": []
              },
              {
                "depth": 3,
                "name": "ComputerNetworksAapplicationsTopic",
                "subClasses": []
              },
              {
                "depth": 3,
                "name": "ComputerNetworksOpticalTopic",
                "subClasses": []
              },
              {
                "depth": 3,
                "name": "ComputerNetworksSensorTopic",
                "subClasses": []
              },
              {
                "depth": 3,
                "name": "ComputerNetworksSwitchingTopic",
                "subClasses": []
              },
              {
                "depth": 3,
                "name": "ComputerNetworksEnterpriseTopic",
                "subClasses": []
              },
              {
                "depth": 3,
                "name": "ComputerNetworksManagementTopic",
                "subClasses": []
              }
            ]
          },
          {
            "depth": 2,
            "name": "PowerlineTransmissionTopic",
            "subClasses": []
          },
          {
            "depth": 2,
            "name": "MobileComputingTopic",
            "subClasses": []
          },
          {
            "depth": 2,
            "name": "PerformanceTopic",
            "subClasses": []
          }
        ]
      },
      {
        "depth": 1,
        "name": "Country",
        "subClasses": []
      },
      {
        "depth": 1,
        "name": "ReviewForm",
        "subClasses": []
      },
      {
        "depth": 1,
        "name": "Author",
        "subClasses": [
          {
            "depth": 2,
            "name": "Presenter",
            "subClasses": []
          }
        ]
      },
      {
        "depth": 1,
        "name": "Reviewer",
        "subClasses": []
      },
      {
        "depth": 1,
        "name": "PersonalHistory",
        "subClasses": [
          {
            "depth": 2,
            "name": "PersonalPublicationHistory",
            "subClasses": []
          },
          {
            "depth": 2,
            "name": "PersonalReviewHistory",
            "subClasses": []
          }
        ]
      },
      {
        "depth": 1,
        "name": "ReviewQuestion",
        "subClasses": [
          {
            "depth": 2,
            "name": "TextualReviewQuestion",
            "subClasses": []
          },
          {
            "depth": 2,
            "name": "NumericalReviewQuestion",
            "subClasses": []
          }
        ]
      },
      {
        "depth": 1,
        "name": "ContactInformation",
        "subClasses": []
      },
      {
        "depth": 1,
        "name": "TwoLevelConference",
        "subClasses": []
      },
      {
        "depth": 1,
        "name": "ConferenceSession",
        "subClasses": []
      },
      {
        "depth": 1,
        "name": "Place",
        "subClasses": [
          {
            "depth": 2,
            "name": "AccommodationPlace",
            "subClasses": []
          },
          {
            "depth": 2,
            "name": "MeetingRoomPlace",
            "subClasses": []
          },
          {
            "depth": 2,
            "name": "DiningPlace",
            "subClasses": []
          },
          {
            "depth": 2,
            "name": "ConferenceVenuePlace",
            "subClasses": []
          }
        ]
      },
      {
        "depth": 1,
        "name": "Sponsorship",
        "subClasses": [
          {
            "depth": 2,
            "name": "TravelGrant",
            "subClasses": []
          }
        ]
      },
      {
        "depth": 1,
        "name": "Organization",
        "subClasses": [
          {
            "depth": 2,
            "name": "AcademiaOrganization",
            "subClasses": []
          },
          {
            "depth": 2,
            "name": "IndustryOrganization",
            "subClasses": []
          },
          {
            "depth": 2,
            "name": "NGO",
            "subClasses": []
          },
          {
            "depth": 2,
            "name": "GovernmentOrganization",
            "subClasses": []
          }
        ]
      },
      {
        "depth": 1,
        "name": "Call",
        "subClasses": [
          {
            "depth": 2,
            "name": "CallForManuscripts",
            "subClasses": []
          },
          {
            "depth": 2,
            "name": "CallForReviews",
            "subClasses": []
          },
          {
            "depth": 2,
            "name": "CallForPapers",
            "subClasses": []
          }
        ]
      },
      {
        "depth": 1,
        "name": "Document",
        "subClasses": [
          {
            "depth": 2,
            "name": "SlideSet",
            "subClasses": []
          },
          {
            "depth": 2,
            "name": "MealMenu",
            "subClasses": []
          },
          {
            "depth": 2,
            "name": "Programme",
            "subClasses": []
          },
          {
            "depth": 2,
            "name": "Review",
            "subClasses": []
          },
          {
            "depth": 2,
            "name": "Paper",
            "subClasses": [
              {
                "depth": 3,
                "name": "ActivePaper",
                "subClasses": [
                  {
                    "depth": 4,
                    "name": "RatedPapers",
                    "subClasses": []
                  }
                ]
              },
              {
                "depth": 3,
                "name": "RejectedPaper",
                "subClasses": []
              },
              {
                "depth": 3,
                "name": "PendingPaper",
                "subClasses": []
              },
              {
                "depth": 3,
                "name": "PublishedPaper",
                "subClasses": []
              },
              {
                "depth": 3,
                "name": "WithdrawnPaper",
                "subClasses": []
              },
              {
                "depth": 3,
                "name": "AcceptedPaper",
                "subClasses": []
              }
            ]
          }
        ]
      },
      {
        "depth": 1,
        "name": "ConferenceEvent",
        "subClasses": [
          {
            "depth": 2,
            "name": "NonAcademicEvent",
            "subClasses": [
              {
                "depth": 3,
                "name": "SocialEvent",
                "subClasses": [
                  {
                    "depth": 4,
                    "name": "Reception",
                    "subClasses": []
                  },
                  {
                    "depth": 4,
                    "name": "Excursion",
                    "subClasses": []
                  }
                ]
              },
              {
                "depth": 3,
                "name": "BreakEvent",
                "subClasses": [
                  {
                    "depth": 4,
                    "name": "CoffeeBreak",
                    "subClasses": []
                  },
                  {
                    "depth": 4,
                    "name": "MealBreak",
                    "subClasses": []
                  },
                  {
                    "depth": 4,
                    "name": "FreeTimeBreak",
                    "subClasses": []
                  }
                ]
              },
              {
                "depth": 3,
                "name": "MealEvent",
                "subClasses": [
                  {
                    "depth": 4,
                    "name": "ConferenceDinner",
                    "subClasses": []
                  }
                ]
              }
            ]
          },
          {
            "depth": 2,
            "name": "AcademicEvent",
            "subClasses": [
              {
                "depth": 3,
                "name": "TalkEvent",
                "subClasses": [
                  {
                    "depth": 4,
                    "name": "WelcomeTalk",
                    "subClasses": []
                  },
                  {
                    "depth": 4,
                    "name": "ClosingTalk",
                    "subClasses": []
                  }
                ]
              },
              {
                "depth": 3,
                "name": "PaperPresentation",
                "subClasses": []
              },
              {
                "depth": 3,
                "name": "Workshop",
                "subClasses": []
              },
              {
                "depth": 3,
                "name": "OrganizationalMeeting",
                "subClasses": []
              }
            ]
          }
        ]
      },
      {
        "depth": 1,
        "name": "ReviewRating",
        "subClasses": [
          {
            "depth": 2,
            "name": "AcceptRating",
            "subClasses": []
          },
          {
            "depth": 2,
            "name": "AccpetIfRoomRating",
            "subClasses": []
          },
          {
            "depth": 2,
            "name": "RejectRating",
            "subClasses": []
          },
          {
            "depth": 2,
            "name": "WeekRejectRating",
            "subClasses": []
          }
        ]
      }
    ]
  }
}